owlsensor/__init__.py
owlsensor/const.py
owlsensor/device.py
owlsensor/serial_cm.py
owlsensor-0.5.8.dist-info/licenses/LICENSE
owlsensor-0.5.8.dist-info/METADATA
owlsensor-0.5.8.dist-info/WHEEL
owlsensor-0.5.8.dist-info/top_level.txt
owlsensor-0.5.8.dist-info/RECORD
