Metadata-Version: 2.4
Name: owlsensor
Version: 0.5.8
Summary: Library to read data from OWL Energy meters
Home-page: https://github.com/PBrunot/owlsensor
Author: Pascal Brunot
Author-email: pbr-dev@gmail.com
License: MIT
Keywords: serial owl cm160 energy_meter homeautomation
Classifier: Development Status :: 4 - Beta
Classifier: Intended Audience :: Developers
Classifier: Topic :: System :: Hardware :: Hardware Drivers
Classifier: License :: OSI Approved :: MIT License
Classifier: Programming Language :: Python :: 3
Classifier: Programming Language :: Python :: 3.10
License-File: LICENSE
Requires-Dist: pyserial-asyncio-fast>=0.16
Dynamic: author
Dynamic: author-email
Dynamic: classifier
Dynamic: description
Dynamic: description-content-type
Dynamic: home-page
Dynamic: keywords
Dynamic: license
Dynamic: license-file
Dynamic: requires-dist
Dynamic: summary
